freshsalessdk/__init__.py
freshsalessdk/freshsalessdk.py
test/__init__.py
test/common.py
test/conftest.py
test/test_accounts.py
test/test_contacts.py
test/test_deals.py
freshsalessdk-0.1.3.dist-info/LICENSE
freshsalessdk-0.1.3.dist-info/METADATA
freshsalessdk-0.1.3.dist-info/WHEEL
freshsalessdk-0.1.3.dist-info/top_level.txt
freshsalessdk-0.1.3.dist-info/RECORD
