Metadata-Version: 2.1
Name: freshsalessdk
Version: 0.1.3
Summary: Python SDK for accessing Freshsales
Home-page: https://github.com/fylein/freshsales-sdk-py
Author: Siva Narayanan
Author-email: siva@fyle.in
License: MIT
Keywords: freshsales,api,python,sdk
Platform: UNKNOWN
Classifier: Topic :: Internet :: WWW/HTTP
Classifier: Intended Audience :: Developers
Classifier: Programming Language :: Python :: 3
Classifier: License :: OSI Approved :: MIT License
Classifier: Operating System :: OS Independent
Requires-Dist: requests
